{
	"textures": {
		"0": "modelengine:entity/bozo"
	},
	"elements": [
		{
			"from": [-1.5,7.5,7.5],
			"to":   [7.5,12.5,11.5],
			"faces": {
				"east":  { "uv": [9.25,3.75,8.75,4.375],   "tintindex": 0, "rotation": 0, "bozo": "#0" },
				"south": { "uv": [10.375,3.75,9.25,4.375], "tintindex": 0, "rotation": 0, "bozo": "#0" },
				"north": { "uv": [8.75,3.75,7.625,4.375],  "tintindex": 0, "rotation": 0, "bozo": "#0" },
				"west":  { "uv": [7.625,3.75,7.125,4.375], "tintindex": 0, "rotation": 0, "bozo": "#0" },
				"up":    { "uv": [7.625,3.75,8.75,3.25],   "tintindex": 0, "rotation": 0, "bozo": "#0" },
				"down":  { "uv": [8.75,3.25,9.875,3.75],   "tintindex": 0, "rotation": 0, "bozo": "#0" }
			}
		}
	],
	"display": {
		"gui": {
			"rotation": [30,225,0]
		}
	}
}
